{"assets/images/appdev.png":["assets/images/appdev.png"],"assets/images/backgroundimage.jpeg":["assets/images/backgroundimage.jpeg"],"assets/images/backmail.jpg":["assets/images/backmail.jpg"],"assets/images/chatapp.png":["assets/images/chatapp.png"],"assets/images/csharp.png":["assets/images/csharp.png"],"assets/images/dart.png":["assets/images/dart.png"],"assets/images/dart02.png":["assets/images/dart02.png"],"assets/images/data.png":["assets/images/data.png"],"assets/images/developer.png":["assets/images/developer.png"],"assets/images/ecommerence.png":["assets/images/ecommerence.png"],"assets/images/game-development.png":["assets/images/game-development.png"],"assets/images/github.png":["assets/images/github.png"],"assets/images/image.png":["assets/images/image.png"],"assets/images/instagram.png":["assets/images/instagram.png"],"assets/images/iosicon.png":["assets/images/iosicon.png"],"assets/images/java.png":["assets/images/java.png"],"assets/images/linkedin.png":["assets/images/linkedin.png"],"assets/images/mailbackground.jpg":["assets/images/mailbackground.jpg"],"assets/images/manjumping.jpg":["assets/images/manjumping.jpg"],"assets/images/mansitting.jpg":["assets/images/mansitting.jpg"],"assets/images/messageback.jpg":["assets/images/messageback.jpg"],"assets/images/myprofile01.jpg":["assets/images/myprofile01.jpg"],"assets/images/myprofile02.jpg":["assets/images/myprofile02.jpg"],"assets/images/news.png":["assets/images/news.png"],"assets/images/people.png":["assets/images/people.png"],"assets/images/projecticon.png":["assets/images/projecticon.png"],"assets/images/pyhton.png":["assets/images/pyhton.png"],"assets/images/travelapp.jpeg":["assets/images/travelapp.jpeg"],"assets/images/working.png":["assets/images/working.png"],"packages/cupertino_icons/assets/CupertinoIcons.ttf":["packages/cupertino_icons/assets/CupertinoIcons.ttf"]}